__init__.py
cli.py
config.py
main.py
models.py
core/__init__.py
core/config.py
core/container.py
database/__init__.py
database/connection.py
database/database.py
database/models.py
database/schemas.py
orchesity_ide_oss-1.0.0.dist-info/licenses/LICENSE
routers/__init__.py
routers/database.py
routers/health.py
routers/llm.py
routers/user.py
services/DWA.py
services/__init__.py
services/cache.py
services/cache_new.py
services/database.py
services/dwa_strategies.py
services/health.py
services/llm_orchestrator.py
services/metrics.py
utils/__init__.py
utils/logger.py
orchesity_ide_oss-1.0.0.dist-info/METADATA
orchesity_ide_oss-1.0.0.dist-info/WHEEL
orchesity_ide_oss-1.0.0.dist-info/entry_points.txt
orchesity_ide_oss-1.0.0.dist-info/top_level.txt
orchesity_ide_oss-1.0.0.dist-info/RECORD
