Metadata-Version: 2.4
Name: orchesity-ide-oss
Version: 1.0.0
Summary: Open-source IDE for intelligent Multi-LLM orchestration
Author-email: Kolerr Lab <contact@kolerr-lab.com>
Maintainer-email: Kolerr Lab <contact@kolerr-lab.com>
License: MIT License
Project-URL: Homepage, https://github.com/Kolerr-Lab/Orchesity_IDE_OSS
Project-URL: Documentation, https://orchesity-ide-oss.readthedocs.io/
Project-URL: Repository, https://github.com/Kolerr-Lab/Orchesity_IDE_OSS
Project-URL: Issues, https://github.com/Kolerr-Lab/Orchesity_IDE_OSS/issues
Project-URL: Changelog, https://github.com/Kolerr-Lab/Orchesity_IDE_OSS/blob/main/CHANGELOG.md
Keywords: llm,orchestration,ai,openai,anthropic,gemini,grok,fastapi
Classifier: Development Status :: 4 - Beta
Classifier: Intended Audience :: Developers
Classifier: License :: OSI Approved :: MIT License
Classifier: Operating System :: OS Independent
Classifier: Programming Language :: Python :: 3
Classifier: Programming Language :: Python :: 3.9
Classifier: Programming Language :: Python :: 3.10
Classifier: Programming Language :: Python :: 3.11
Classifier: Programming Language :: Python :: 3.12
Classifier: Topic :: Scientific/Engineering :: Artificial Intelligence
Classifier: Topic :: Software Development :: Libraries :: Python Modules
Requires-Python: >=3.9
License-File: LICENSE
Requires-Dist: fastapi>=0.104.0
Requires-Dist: uvicorn[standard]>=0.24.0
Requires-Dist: pydantic>=2.0.0
Requires-Dist: pydantic-settings>=2.0.0
Requires-Dist: python-multipart>=0.0.6
Requires-Dist: httpx>=0.25.0
Requires-Dist: psutil>=5.9.0
Provides-Extra: dev
Requires-Dist: pytest>=7.0.0; extra == "dev"
Requires-Dist: pytest-cov>=4.0.0; extra == "dev"
Requires-Dist: black>=23.0.0; extra == "dev"
Requires-Dist: isort>=5.12.0; extra == "dev"
Requires-Dist: flake8>=6.0.0; extra == "dev"
Requires-Dist: mypy>=1.0.0; extra == "dev"
Requires-Dist: bandit>=1.7.0; extra == "dev"
Requires-Dist: safety>=2.3.0; extra == "dev"
Provides-Extra: docs
Requires-Dist: mkdocs>=1.5.0; extra == "docs"
Requires-Dist: mkdocs-material>=9.0.0; extra == "docs"
Dynamic: license-file
